pyNN/__init__.py
pyNN/connectors.py
pyNN/core.py
pyNN/errors.py
pyNN/models.py
pyNN/morphology.py
pyNN/multisim.py
pyNN/network.py
pyNN/parameters.py
pyNN/random.py
pyNN/space.py
pyNN/spiNNaker.py
pyNN/arbor/__init__.py
pyNN/arbor/cells.py
pyNN/arbor/control.py
pyNN/arbor/morphology.py
pyNN/arbor/populations.py
pyNN/arbor/procedural_api.py
pyNN/arbor/projections.py
pyNN/arbor/recording.py
pyNN/arbor/simulator.py
pyNN/arbor/standardmodels.py
pyNN/arbor/nmodl/expsyn.mod
pyNN/arbor/nmodl/kdr.mod
pyNN/arbor/nmodl/leak.mod
pyNN/arbor/nmodl/na.mod
pyNN/arbor/nmodl/pas.mod
pyNN/arbor/nmodl/pas2.mod
pyNN/brian2/__init__.py
pyNN/brian2/cells.py
pyNN/brian2/control.py
pyNN/brian2/populations.py
pyNN/brian2/procedural_api.py
pyNN/brian2/projections.py
pyNN/brian2/recording.py
pyNN/brian2/simulator.py
pyNN/brian2/standardmodels/__init__.py
pyNN/brian2/standardmodels/cells.py
pyNN/brian2/standardmodels/electrodes.py
pyNN/brian2/standardmodels/receptors.py
pyNN/brian2/standardmodels/synapses.py
pyNN/common/__init__.py
pyNN/common/control.py
pyNN/common/populations.py
pyNN/common/procedural_api.py
pyNN/common/projections.py
pyNN/descriptions/__init__.py
pyNN/descriptions/templates/cheetah/assembly_default.txt
pyNN/descriptions/templates/cheetah/modeltype_default.txt
pyNN/descriptions/templates/cheetah/population_default.txt
pyNN/descriptions/templates/cheetah/populationview_default.txt
pyNN/descriptions/templates/cheetah/projection_default.txt
pyNN/descriptions/templates/cheetah/structure_default.txt
pyNN/descriptions/templates/cheetah/synapsedynamics_default.txt
pyNN/descriptions/templates/jinja2/assembly_default.txt
pyNN/descriptions/templates/jinja2/modeltype_default.txt
pyNN/descriptions/templates/jinja2/population_default.txt
pyNN/descriptions/templates/jinja2/populationview_default.txt
pyNN/descriptions/templates/jinja2/projection_default.txt
pyNN/descriptions/templates/jinja2/structure_default.txt
pyNN/descriptions/templates/jinja2/synapsedynamics_default.txt
PyNN-0.12.3.dist-info/AUTHORS
PyNN-0.12.3.dist-info/LICENSE
PyNN-0.12.3.dist-info/METADATA
PyNN-0.12.3.dist-info/WHEEL
PyNN-0.12.3.dist-info/top_level.txt
PyNN-0.12.3.dist-info/RECORD
