Metadata-Version: 2.1
Name: PyNN
Version: 0.12.3
Summary: A Python package for simulator-independent specification of neuronal network models
Author-email: The PyNN team <pynn-maintainers@protonmail.com>
Maintainer-email: The PyNN team <pynn-maintainers@protonmail.com>
License: CeCILL http://www.cecill.info
Project-URL: homepage, http://neuralensemble.org/PyNN/
Project-URL: documentation, http://neuralensemble.org/docs/PyNN/
Project-URL: repository, https://github.com/NeuralEnsemble/PyNN
Project-URL: changelog, http://neuralensemble.org/docs/PyNN/release_notes.html
Project-URL: download, http://pypi.python.org/pypi/PyNN
Keywords: computational neuroscience, simulation, neuron, nest, brian2, neuromorphic
Classifier: Development Status :: 4 - Beta
Classifier: Environment :: Console
Classifier: Intended Audience :: Science/Research
Classifier: License :: OSI Approved :: CEA CNRS Inria Logiciel Libre License, version 2.1 (CeCILL-2.1)
Classifier: Natural Language :: English
Classifier: Operating System :: OS Independent
Classifier: Programming Language :: Python :: 3
Classifier: Programming Language :: Python :: 3.8
Classifier: Programming Language :: Python :: 3.9
Classifier: Programming Language :: Python :: 3.10
Classifier: Programming Language :: Python :: 3.11
Classifier: Programming Language :: Python :: 3.12
Classifier: Topic :: Education
Classifier: Topic :: Scientific/Engineering
Requires-Python: >=3.8
License-File: LICENSE
License-File: AUTHORS
Requires-Dist: numpy >=1.18.5
Requires-Dist: lazyarray >=0.5.2
Requires-Dist: neo >=0.11.0
Requires-Dist: quantities >=0.12.1
Requires-Dist: morphio
Provides-Extra: mpi
Requires-Dist: mpi4py ; extra == 'mpi'
Provides-Extra: arbor
Requires-Dist: arbor ; extra == 'arbor'
Provides-Extra: brian2
Requires-Dist: brian2 ; extra == 'brian2'
Provides-Extra: doc
Requires-Dist: sphinx ; extra == 'doc'
Provides-Extra: examples
Requires-Dist: matplotlib ; extra == 'examples'
Requires-Dist: scipy ; extra == 'examples'
Provides-Extra: neuroml
Requires-Dist: libNeuroML ; extra == 'neuroml'
Provides-Extra: neuron
Requires-Dist: neuron ; extra == 'neuron'
Requires-Dist: nrnutils ; extra == 'neuron'
Provides-Extra: plotting
Requires-Dist: matplotlib ; extra == 'plotting'
Requires-Dist: scipy ; extra == 'plotting'
Provides-Extra: sonata
Requires-Dist: h5py ; extra == 'sonata'
Provides-Extra: spinnaker
Requires-Dist: spyNNaker ; extra == 'spinnaker'
Provides-Extra: test
Requires-Dist: pytest ; extra == 'test'
Requires-Dist: pytest-cov ; extra == 'test'
Requires-Dist: flake8 ; extra == 'test'
Requires-Dist: wheel ; extra == 'test'
Requires-Dist: mpi4py ; extra == 'test'
Requires-Dist: scipy ; extra == 'test'
Requires-Dist: matplotlib ; extra == 'test'
Requires-Dist: Cheetah3 ; extra == 'test'
Requires-Dist: h5py ; extra == 'test'
Requires-Dist: Jinja2 ; extra == 'test'
